flowdyn/__init__.py
flowdyn/_data.py
flowdyn/field.py
flowdyn/integration.py
flowdyn/mesh.py
flowdyn/mesh2d.py
flowdyn/meshbase.py
flowdyn/modeldisc.py
flowdyn/modelphy/__init__.py
flowdyn/modelphy/base.py
flowdyn/modelphy/burgers.py
flowdyn/modelphy/convection.py
flowdyn/modelphy/euler.py
flowdyn/modelphy/shallowwater.py
flowdyn/monitors.py
flowdyn/solution/__init__.py
flowdyn/solution/euler_nozzle.py
flowdyn/solution/euler_riemann.py
flowdyn/xnum.py
flowdyn-1.3.1.dist-info/WHEEL
flowdyn-1.3.1.dist-info/METADATA
flowdyn-1.3.1.dist-info/RECORD
